[
  {
    "K": 8,
    "seed": 0,
    "amm_pretrain_steps": 537,
    "amm_pretrain_acc": 0.9911,
    "amm_old_acc_before": 1.0,
    "amm_new_acc_before": 0.0,
    "amm_slots_bound": 8,
    "amm_new_acc_after_bind": 0.0,
    "lstm_pretrain_steps": 532,
    "lstm_pretrain_acc": 0.9914,
    "lstm_old_acc_before": 1.0,
    "lstm_new_acc_before": 0.0,
    "amm_finetune_to_90": 471,
    "lstm_finetune_to_90": 525
  },
  {
    "K": 8,
    "seed": 1,
    "amm_pretrain_steps": 563,
    "amm_pretrain_acc": 0.9906,
    "amm_old_acc_before": 1.0,
    "amm_new_acc_before": 0.0,
    "amm_slots_bound": 8,
    "amm_new_acc_after_bind": 0.0,
    "lstm_pretrain_steps": 561,
    "lstm_pretrain_acc": 0.9902,
    "lstm_old_acc_before": 1.0,
    "lstm_new_acc_before": 0.0,
    "amm_finetune_to_90": 478,
    "lstm_finetune_to_90": 531
  },
  {
    "K": 8,
    "seed": 2,
    "amm_pretrain_steps": 550,
    "amm_pretrain_acc": 0.9911,
    "amm_old_acc_before": 1.0,
    "amm_new_acc_before": 0.0,
    "amm_slots_bound": 8,
    "amm_new_acc_after_bind": 0.0,
    "lstm_pretrain_steps": 527,
    "lstm_pretrain_acc": 0.9912,
    "lstm_old_acc_before": 1.0,
    "lstm_new_acc_before": 0.0,
    "amm_finetune_to_90": 507,
    "lstm_finetune_to_90": 536
  },
  {
    "K": 16,
    "seed": 0,
    "amm_pretrain_steps": 650,
    "amm_pretrain_acc": 0.99,
    "amm_old_acc_before": 1.0,
    "amm_new_acc_before": 0.0,
    "amm_slots_bound": 16,
    "amm_new_acc_after_bind": 0.0,
    "lstm_pretrain_steps": 608,
    "lstm_pretrain_acc": 0.9912,
    "lstm_old_acc_before": 1.0,
    "lstm_new_acc_before": 0.0,
    "amm_finetune_to_90": 398,
    "lstm_finetune_to_90": 437
  },
  {
    "K": 16,
    "seed": 1,
    "amm_pretrain_steps": 659,
    "amm_pretrain_acc": 0.9911,
    "amm_old_acc_before": 1.0,
    "amm_new_acc_before": 0.0,
    "amm_slots_bound": 16,
    "amm_new_acc_after_bind": 0.0,
    "lstm_pretrain_steps": 633,
    "lstm_pretrain_acc": 0.99,
    "lstm_old_acc_before": 1.0,
    "lstm_new_acc_before": 0.0,
    "amm_finetune_to_90": 403,
    "lstm_finetune_to_90": 481
  },
  {
    "K": 16,
    "seed": 2,
    "amm_pretrain_steps": 688,
    "amm_pretrain_acc": 0.9908,
    "amm_old_acc_before": 1.0,
    "amm_new_acc_before": 0.0,
    "amm_slots_bound": 16,
    "amm_new_acc_after_bind": 0.0,
    "lstm_pretrain_steps": 626,
    "lstm_pretrain_acc": 0.9908,
    "lstm_old_acc_before": 1.0,
    "lstm_new_acc_before": 0.0,
    "amm_finetune_to_90": 429,
    "lstm_finetune_to_90": 458
  },
  {
    "K": 32,
    "seed": 0,
    "amm_pretrain_steps": 684,
    "amm_pretrain_acc": 0.9902,
    "amm_old_acc_before": 1.0,
    "amm_new_acc_before": 0.0312,
    "amm_slots_bound": 32,
    "amm_new_acc_after_bind": 0.0353,
    "lstm_pretrain_steps": 696,
    "lstm_pretrain_acc": 0.99,
    "lstm_old_acc_before": 1.0,
    "lstm_new_acc_before": 0.0331,
    "amm_finetune_to_90": 421,
    "lstm_finetune_to_90": 493
  },
  {
    "K": 32,
    "seed": 1,
    "amm_pretrain_steps": 672,
    "amm_pretrain_acc": 0.9905,
    "amm_old_acc_before": 1.0,
    "amm_new_acc_before": 0.0309,
    "amm_slots_bound": 32,
    "amm_new_acc_after_bind": 0.0291,
    "lstm_pretrain_steps": 661,
    "lstm_pretrain_acc": 0.9902,
    "lstm_old_acc_before": 1.0,
    "lstm_new_acc_before": 0.0291,
    "amm_finetune_to_90": 419,
    "lstm_finetune_to_90": 464
  },
  {
    "K": 32,
    "seed": 2,
    "amm_pretrain_steps": 696,
    "amm_pretrain_acc": 0.99,
    "amm_old_acc_before": 1.0,
    "amm_new_acc_before": 0.0312,
    "amm_slots_bound": 32,
    "amm_new_acc_after_bind": 0.0312,
    "lstm_pretrain_steps": 664,
    "lstm_pretrain_acc": 0.9905,
    "lstm_old_acc_before": 1.0,
    "lstm_new_acc_before": 0.0259,
    "amm_finetune_to_90": 437,
    "lstm_finetune_to_90": 469
  }
]